autolunch/__init__.py
autolunch/app.py
autolunch/cli.py
lunchable_autolunch-0.1.2.dist-info/METADATA
lunchable_autolunch-0.1.2.dist-info/WHEEL
lunchable_autolunch-0.1.2.dist-info/entry_points.txt
lunchable_autolunch-0.1.2.dist-info/licenses/LICENSE
lunchable_autolunch-0.1.2.dist-info/RECORD
