Metadata-Version: 2.1
Name: lunchable-autolunch
Version: 0.1.2
Summary: Automatically rename merchant names and autocategorise transactions.
Author-Email: LightQuantum <self@lightquantum.me>
License: MIT
Requires-Python: >=3.10
Requires-Dist: click>=8.1.8
Requires-Dist: lunchable>=1.4.2
Requires-Dist: rich>=13.9.4
Requires-Dist: openai>=1.68.2
Requires-Dist: questionary>=2.1.0
Requires-Dist: pydantic>=2.10.6
Requires-Dist: readchar>=4.2.1
Requires-Dist: copykitten>=1.2.2
Requires-Dist: fuzzyfinder>=2.2.0
Requires-Dist: thefuzz>=0.22.1
